aiormq_lib/__init__.py
aiormq_lib/abc/__init__.py
aiormq_lib/abc/api.py
aiormq_lib/abc/client.py
aiormq_lib/abc/connection.py
aiormq_lib/abc/listener.py
aiormq_lib/abc/queue.py
aiormq_lib/core.py
aiormq_lib/exceptions.py
aiormq_lib/mixins/__init__.py
aiormq_lib/mixins/api_mixins.py
aiormq_lib/mixins/connection_mixin.py
aiormq_lib/mixins/listener_mixin.py
aiormq_lib/mixins/queue_mixin.py
aiormq_lib/models/__init__.py
aiormq_lib/models/channel.py
aiormq_lib/models/connection.py
aiormq_lib/models/filter.py
aiormq_lib/models/listener.py
aiormq_lib/models/message.py
aiormq_lib/models/queue.py
aiormq_lib/models/queue_handler.py
aiormq_lib-0.1.7.dist-info/LICENSE
aiormq_lib-0.1.7.dist-info/METADATA
aiormq_lib-0.1.7.dist-info/WHEEL
aiormq_lib-0.1.7.dist-info/RECORD
