Metadata-Version: 2.3
Name: aiormq_lib
Version: 0.1.7
Summary: Package for working with RabbitMQ
License: MIT
Author: MentorSisek
Author-email: n3m0_22@mail.ru
Requires-Python: >=3.10, <4.0
Classifier: License :: OSI Approved :: MIT License
Classifier: Programming Language :: Python :: 3
Classifier: Programming Language :: Python :: 3.10
Classifier: Programming Language :: Python :: 3.11
Classifier: Programming Language :: Python :: 3.12
Classifier: Programming Language :: Python :: 3.13
Requires-Dist: aio-pika (>=9.5.5,<10.0.0)
Requires-Dist: aiohttp (>=3.11.14,<4.0.0)
Project-URL: Homepage, https://github.com/Tsunami43/aiormq_lib.git
